RTL_DivyaDarshan/Full Adder/full_adder.v
module full_adder(input a,b,c,output sum,carry);

assign sum = a^b^c;
assign carry = (a&b) | (b&c) | (c&a) ;

endmodule

RTL_DivyaDarshan/Full Adder/full_adder_tb.v
`include "full_adder.v"
module full_adder_tb();
  reg a,b,c;
  wire sum,carry;
  
  full_adder FA (a,b,c,sum,carry);

  initial begin
    $dumpfile("full_adder_tb.vcd");
    $dumpvars(0,full_adder_tb);

    a=0;b=0;c=0; #10;
    a=0;b=0;c=1; #10;
    a=0;b=1;c=0; #10;
    a=0;b=1;c=1; #10;
    a=1;b=0;c=0; #10;
    a=1;b=0;c=1; #10;
    a=1;b=1;c=0; #10;
    a=1;b=1;c=1; #10;

  end

endmodule

RTL_DivyaDarshan/Full Adder/full_adder_tb.vcd
$date
	Mon Jun 02 23:02:46 2025
$end
$version
	Icarus Verilog
$end
$timescale
	1s
$end
$scope module full_adder_tb $end
$var wire 1 ! carry $end
$var wire 1 " sum $end
$var reg 1 # a $end
$var reg 1 $ b $end
$var reg 1 % c $end
$scope module FA $end
$var wire 1 & a $end
$var wire 1 ' b $end
$var wire 1 ( c $end
$var wire 1 ! carry $end
$var wire 1 " sum $end
$upscope $end
$upscope $end
$enddefinitions $end
#0
$dumpvars
0(
0'
0&
0%
0$
0#
0"
0!
$end
#10
1"
1%
1(
#20
0%
0(
1$
1'
#30
1!
0"
1%
1(
#40
0!
1"
0%
0(
0$
0'
1#
1&
#50
1!
0"
1%
1(
#60
0%
0(
1$
1'
#70
1"
1%
1(
